rusev_py-0.1.0.dist-info/METADATA
rusev_py-0.1.0.dist-info/WHEEL
rusev_py/rusev.py
rusev_py/py.typed
rusev_py/rusev_py.cpython-313-x86_64-linux-gnu.so
rusev_py-0.1.0.dist-info/RECORD
